RunningTrainsPlot/__init__.py
RunningTrainsPlot/column_flow/__init__.py
RunningTrainsPlot/cyclic_diagram/__init__.py
RunningTrainsPlot/examples/__init__.py
RunningTrainsPlot/passenger_flow/__init__.py
RunningTrainsPlot/speed_curve/__init__.py
RunningTrainsPlot/stock_channel/__init__.py
RunningTrainsPlot/track_occupation/__init__.py
RunningTrainsPlot/utils/__init__.py
runningtrainsplot-1.0.7.dist-info/METADATA
runningtrainsplot-1.0.7.dist-info/WHEEL
runningtrainsplot-1.0.7.dist-info/top_level.txt
runningtrainsplot-1.0.7.dist-info/RECORD
