Metadata-Version: 2.4
Name: RunningTrainsPlot
Version: 1.0.7
Summary: 铁路列车运行数据可视化工具
Home-page: https://github.com/yourusername/RunningTrainsPlot
Author: Shen-Zeyu,Guan-Chengze,Zheng-Haoyu,He-Zelin,Wu-Yuqian
Author-email: sc22zs2@leeds.ac.uk
Keywords: railway,train,visualization,plot,diagram,flow
Classifier: Programming Language :: Python :: 3
Classifier: License :: OSI Approved :: MIT License
Classifier: Operating System :: OS Independent
Requires-Python: >=3.6
Requires-Dist: pandas>=1.0.0
Requires-Dist: numpy>=1.18.0
Requires-Dist: matplotlib>=3.1.0
Requires-Dist: plotly>=5.0.0
Dynamic: author
Dynamic: author-email
Dynamic: classifier
Dynamic: description
Dynamic: description-content-type
Dynamic: home-page
Dynamic: keywords
Dynamic: requires-dist
Dynamic: requires-python
Dynamic: summary
